[
  {
    "word": "indication",
    "meaning": ["징후"]
  },
  {
    "word": "indicator",
    "meaning": ["지표"]
  },
    {
    "word": "warn",
    "meaning": ["경고하다"]
  },
  {
    "word": "depression",
    "meaning": ["불황"]
  },
  {
    "word": "prospect",
    "meaning": ["예상", "전망"]
  },
  {
    "word": "lead",
    "meaning": ["이끌다", "~에 이르다"]
  },
  {
    "word": "economical",
    "meaning": ["경제적인", "절약되는"]
  },
  {
    "word": "brisk",
    "meaning": ["호황의", "활발한"]
  },
  {
    "word": "refund",
    "meaning": ["환불", "환불금", "환불하다"]
  },
  {
    "word": "offer",
    "meaning": ["제공하다", "제안하다", "제안"]
  },
  {
    "word": "redeemable",
    "meaning": ["교환할 수 있는"]
  },
  {
    "word": "installment",
    "meaning": ["할부"]
  },
  {
    "word": "installation",
    "meaning": ["설치", "시설", "장치"]
  },
  {
    "word": "spare",
    "meaning": ["아끼다", "할애하다", "여분의"]
  },
  {
    "word": "exclusively",
    "meaning": ["독점적으로", "오로지"]
  },
  {
    "word": "exclude",
    "meaning": ["제외하다", "거부하다"]
  },
  {
    "word": "notice",
    "meaning": ["통지", "알아채다"]
  },
  {
    "word": "acceptable",
    "meaning": ["받아들일 수 있는"]
  },
  {
    "word": "alter",
    "meaning": ["변경하다", "고치다"]
  },
  {
    "word": "desire",
    "meaning": ["욕구", "바라다"]
  },
  {
    "word": "affordable",
    "meaning": ["감당할 수 있는"]
  },
  {
    "word": "vendor",
    "meaning": ["판매회사", "노점상"]
  },
  {
    "word": "clearance",
    "meaning": ["정리", "허가"]
  },
  {
    "word": "",
    "meaning": [""]
  },
  {
    "word": "",
    "meaning": [""]
  },
  {
    "word": "",
    "meaning": [""]
  },
  {
    "word": "",
    "meaning": [""]
  },
  {
    "word": "",
    "meaning": [""]
  },
  {
    "word": "",
    "meaning": [""]
  },
  {
    "word": "",
    "meaning": [""]
  },
  {
    "word": "",
    "meaning": [""]
  },
  {
    "word": "",
    "meaning": [""]
  },
  {
    "word": "",
    "meaning": [""]
  },
  {
    "word": "",
    "meaning": [""]
  },
  {
    "word": "",
    "meaning": [""]
  },
  {
    "word": "",
    "meaning": [""]
  },
  {
    "word": "",
    "meaning": [""]
  },
  {
    "word": "",
    "meaning": [""]
  },
  {
    "word": "",
    "meaning": [""]
  },
  {
    "word": "",
    "meaning": [""]
  },
  {
    "word": "",
    "meaning": [""]
  },
  {
    "word": "",
    "meaning": [""]
  },
  {
    "word": "",
    "meaning": [""]
  },
  {
    "word": "",
    "meaning": [""]
  },
  {
    "word": "",
    "meaning": [""]
  },
  {
    "word": "",
    "meaning": [""]
  },
  {
    "word": "",
    "meaning": [""]
  },
  {
    "word": "",
    "meaning": [""]
  },
  {
    "word": "",
    "meaning": [""]
  },
  {
    "word": "",
    "meaning": [""]
  }
]
